TODO
setup.cfg
setup.py
gw20e/__init__.py
gw20e.forms.egg-info/PKG-INFO
gw20e.forms.egg-info/SOURCES.txt
gw20e.forms.egg-info/dependency_links.txt
gw20e.forms.egg-info/entry_points.txt
gw20e.forms.egg-info/not-zip-safe
gw20e.forms.egg-info/requires.txt
gw20e.forms.egg-info/top_level.txt
gw20e/forms/README.txt
gw20e/forms/__init__.py
gw20e/forms/form.py
gw20e/forms/formdata.py
gw20e/forms/formmodel.py
gw20e/forms/formview.py
gw20e/forms/interfaces.py
gw20e/forms/atct/__init__.py
gw20e/forms/data/__init__.py
gw20e/forms/data/field.py
gw20e/forms/model/__init__.py
gw20e/forms/model/converters.py
gw20e/forms/model/fieldproperties.py
gw20e/forms/plone/README.txt
gw20e/forms/plone/__init__.py
gw20e/forms/plone/ajaxvalidator.py
gw20e/forms/plone/atctbaseobject.py
gw20e/forms/plone/metadirectives.py
gw20e/forms/plone/view.pt
gw20e/forms/plone/view.py
gw20e/forms/pyramid/README.txt
gw20e/forms/pyramid/__init__.py
gw20e/forms/pyramid/formview.py
gw20e/forms/rendering/__init__.py
gw20e/forms/rendering/baserenderer.py
gw20e/forms/rendering/control.py
gw20e/forms/rendering/controlgroup.py
gw20e/forms/rendering/group.py
gw20e/forms/rendering/interfaces.py
gw20e/forms/rendering/renderables.py
gw20e/forms/rendering/html/__init__.py
gw20e/forms/rendering/html/cardgroup.py
gw20e/forms/rendering/html/checkbox.py
gw20e/forms/rendering/html/colorpicker.py
gw20e/forms/rendering/html/file.py
gw20e/forms/rendering/html/flowgroup.py
gw20e/forms/rendering/html/input.py
gw20e/forms/rendering/html/renderer.py
gw20e/forms/rendering/html/richtext.py
gw20e/forms/rendering/html/select.py
gw20e/forms/rendering/html/selectall.py
gw20e/forms/rendering/html/stepgroup.py
gw20e/forms/rendering/html/submit.py
gw20e/forms/rendering/html/templates.py
gw20e/forms/rendering/html/text.py
gw20e/forms/submission/__init__.py
gw20e/forms/submission/attrstorage.py
gw20e/forms/submission/emailsubmission.py
gw20e/forms/submission/interfaces.py
gw20e/forms/submission/none.py
gw20e/forms/submission/submission.py
gw20e/forms/tests/__init__.py
gw20e/forms/tests/test_doctests.py
gw20e/forms/xml/README.txt
gw20e/forms/xml/__init__.py
gw20e/forms/xml/cache.py
gw20e/forms/xml/factory.py
gw20e/forms/xml/formfile.py
gw20e/forms/xml/gw20e_forms.dtd
